naivenlp_datasets/__init__.py
naivenlp_datasets/charlevel_tokenizer.py
naivenlp_datasets/masked_lm.py
naivenlp_datasets/parsers.py
naivenlp_datasets/question_answering.py
naivenlp_datasets/readers.py
naivenlp_datasets/sequence_classification.py
naivenlp_datasets/simcse.py
naivenlp_datasets/token_classification.py
naivenlp_datasets/pt/__init__.py
naivenlp_datasets/pt/dataset.py
naivenlp_datasets/pt/masked_lm_dataset.py
naivenlp_datasets/pt/question_answering_dataset.py
naivenlp_datasets/pt/sequence_classification_dataset.py
naivenlp_datasets/pt/simcse_dataset.py
naivenlp_datasets/pt/token_classification_dataset.py
naivenlp_datasets/pt/utils.py
naivenlp_datasets/tf/__init__.py
naivenlp_datasets/tf/dataset.py
naivenlp_datasets/tf/masked_lm_dataset.py
naivenlp_datasets/tf/question_answering_dataset.py
naivenlp_datasets/tf/sequence_classification_dataset.py
naivenlp_datasets/tf/simcse_dataset.py
naivenlp_datasets/tf/token_classification_dataset.py
naivenlp_datasets/tf/utils.py
tests/__init__.py
tests/charlevel_tokenizer_test.py
tests/masked_lm_test.py
tests/question_answering_test.py
tests/sequence_classification_test.py
tests/simcse_test.py
tests/token_classification_test.py
naivenlp_datasets-0.1.0.dist-info/LICENSE
naivenlp_datasets-0.1.0.dist-info/METADATA
naivenlp_datasets-0.1.0.dist-info/WHEEL
naivenlp_datasets-0.1.0.dist-info/top_level.txt
naivenlp_datasets-0.1.0.dist-info/RECORD
